README.md
billing/__init__.py
billing/_billing_client.py
billing/_constants.py
billing/_exceptions.py
billing/_http_client.py
billing/_utils.py
billing/_webhook.py
billing/py.typed
billing/services/__init__.py
billing/services/_agreement_api_service.py
billing/services/_billing_api_service.py
billing/services/_customer_api_service.py
billing/services/_feature_api_service.py
billing/services/_invoice_api_service.py
billing/services/_offer_api_service.py
billing/services/_order_api_service.py
billing/services/_product_service.py
billing/types/__init__.py
billing/types/_agreement.py
billing/types/_billing_entity.py
billing/types/_combined.py
billing/types/_common.py
billing/types/_customer.py
billing/types/_feature.py
billing/types/_httpx_payload.py
billing/types/_image.py
billing/types/_invoice.py
billing/types/_invoice_item.py
billing/types/_offer.py
billing/types/_offer_product_plan.py
billing/types/_order.py
billing/types/_product.py
billing/types/_product_plan.py
billing/types/_webhook_event.py
py.typed
billing_sdk-0.7.5.dist-info/LICENSE
billing_sdk-0.7.5.dist-info/METADATA
billing_sdk-0.7.5.dist-info/WHEEL
billing_sdk-0.7.5.dist-info/RECORD
