Metadata-Version: 2.1
Name: billing-sdk
Version: 0.7.5
Summary: 
Home-page: https://gitlab.mypath.group/my-path/billing-sdk
License: MIT
Author: Pavel Prokhorenko
Author-email: p.prohorenko@mypath.group
Requires-Python: >=3.8,<4.0
Classifier: Environment :: Web Environment
Classifier: Framework :: AsyncIO
Classifier: Framework :: Pydantic :: 1
Classifier: Intended Audience :: Developers
Classifier: Intended Audience :: Information Technology
Classifier: Intended Audience :: System Administrators
Classifier: License :: OSI Approved :: MIT License
Classifier: Operating System :: OS Independent
Classifier: Programming Language :: Python
Classifier: Programming Language :: Python :: 3
Classifier: Programming Language :: Python :: 3.8
Classifier: Programming Language :: Python :: 3.9
Classifier: Programming Language :: Python :: 3.10
Classifier: Programming Language :: Python :: 3.11
Classifier: Programming Language :: Python :: 3.12
Classifier: Programming Language :: Python :: 3.13
Classifier: Programming Language :: Python :: 3 :: Only
Classifier: Topic :: Internet
Classifier: Topic :: Internet :: WWW/HTTP
Classifier: Topic :: Internet :: WWW/HTTP :: HTTP Servers
Classifier: Topic :: Software Development
Classifier: Topic :: Software Development :: Libraries
Classifier: Topic :: Software Development :: Libraries :: Python Modules
Classifier: Typing :: Typed
Requires-Dist: httpx (>=0.24,<1.0)
Requires-Dist: pydantic (>=1.7,<3.0)
Project-URL: Repository, https://gitlab.mypath.group/my-path/billing-sdk
